{
  "alphabets_caps": {
    "A": {
      "target": "A",
      "data": 5935584629758,
      "hash": "ma81r;lT*Q0G`F=:U;b;A8I)I#:*M%bW1a6-2kI5wcFq;sT-I`G~H-UM+ml+{}FadWninCq;N*Y&jzKSmw{g<jwl!UC>RnbqF&.)"
    },
    "B": {
      "target": "B",
      "data": 8518654020501,
      "hash": "_U*Trz(_|0u?ZDbM&#fyp?90{pzvoa=]>=p-i0vYYGhAYKIeGS`W3}:yNu/@:b/4)Mz*}Syr*@*gJw3We2xIX{w{h`-,pr!j7f)P"
    },
    "C": {
      "target": "C",
      "data": 4598401343806,
      "hash": "`uUX/^61/LT*1Z2cu*:C?I^:?I,n(]nf%c]]Y-c2GuP68ZODHG{3VUPV<3ksn&&u!8}0;&+n{_5ZAIX8?0+Ir{`)R[Ytdhw=zN]f"
    },
    "D": {
      "target": "D",
      "data": 8255557440342,
      "hash": "*0gq0M-w&VdQC8e9*tZ69If)cH5?=uD}6FtouuG>+$#xNk!;AsA-JCQSV`9UO*$;[G6rEv/xT*KF{`tc^@AQEb/KV(v4FbOITIo?"
    },
    "E": {
      "target": "E",
      "data": 1497060628246,
      "hash": "&fZS$TQgk,$DmWp!I`,lIC4/]G*:2vFY9j_Y~b+;1rt6GyXZ*;y>vfajO@E+6DU+w{J{3`}PE.T}w[(Qr-qtkW2$-ec-K=Z#-fOJ"
    },
    "F": {
      "target": "F",
      "data": 2592924147263,
      "hash": "_3lo^I@ieUBWxXBlE5N=/{Z5{D][5nEC?@L!so.xRM(CP=>DG*uT^7^?DFY]_gTA`GpflIBFs%0Fb^>yt?Af[m=~u.kN@OLw6-fC"
    },
    "G": {
      "target": "G",
      "data": 8174266205650,
      "hash": "OZ_si!OpY|rswy3a<Y1gOh,8s^H?Qsy,VLa#Zl4SuG`=kb,Q^w!~t|JZmM:#7Y)kjtn?u]Gy7u`!XATu:ytFWg/UZ40}uN~jA0w0"
    },
    "H": {
      "target": "H",
      "data": 4489267581390,
      "hash": "a`}Y>@QdX[gz]?}I@02Eb`}>->h[#o!&_}}JOQ,W^]r`GJt=2h4)ts6[yC;e#ol_nL3j;CvA!.a4=(hNb5qyToW#A?&SF$O>VZ*q"
    },
    "I": {
      "target": "I",
      "data": 8950916008309,
      "hash": "i?uhBbOCz:(Av*pw<b*JwI~m8i`C-MaIb9jSy@U1{D2/*IWQ$Z$jJGESRoa=Qxga{C;E*G)e+H;TtRlTudp.^-^lJF&gXaz!~?[t"
    },
    "J": {
      "target": "J",
      "data": 1547384592829,
      "hash": "u5Bq%G+eKDe_wm>19;`pH;V|Yhi$H1=[]P_$B<nVq;2EWS-Ou?7DkjS*.?=9L,Y0,x^<H|P363~B7-dz[M(y,s?-~V:&q:PP*u};"
    },
    "K": {
      "target": "K",
      "data": 9431753087971,
      "hash": "So(`_3eRp1hh_zPQ[H[$aUhn`;*nZ6Z3!JS/x*g&}`bQv:dA$wBV>s#=1VX7l=%6Rz#:R*nz(@9UsRv8<pk]~rK$`e%y,q,8MC%_"
    },
    "L": {
      "target": "L",
      "data": 8961627239691,
      "hash": "UxluN-H@gt*1|<[=>vm`M#=ZOQG`]i40vf|*b&EX=u:T`v4OCn~SmX8/JY0.|mm2#@)T[~;DXnrO(:og;o(dSRFzfJl!$:`FD-&."
    },
    "M": {
      "target": "M",
      "data": 7225197359399,
      "hash": "wrp04$}K9yoUOh:R[.z`J*`+!ga=w8vdODliGs`SV%T?C]K@49E|-WBN{Q!z#}Q_0hGZ&O}w}MbK<;m];1ga099)9^M</@anBn@*"
    },
    "N": {
      "target": "N",
      "data": 5511901538873,
      "hash": "2KpR,b~fcs3`AQy.stF0:J~&,c;dY~F;i5d|5Z+qm:<;b,4t!`{?N*zRO:Vvr8[I0h/0F*8%*ryTtTfd}#~0,h1?Y8q@B^2E^sJ]"
    },
    "O": {
      "target": "O",
      "data": 1765342110530,
      "hash": "pVpIoxW}vveUbh*@D*I[Sw0%(is;:mVcrRSoFHf#o`ZniBIRC1QZ*g`K:]A]`[/lnJR>:[HC{iIy}+&}n9F)EJVhoi*yB/b$6Gwi"
    },
    "P": {
      "target": "P",
      "data": 2157383061287,
      "hash": "^^pf+}s0XJFe{_Sr+8c#a:=+N)q8+xL%^5aBXvOk[-a#o^CV6;pRC(v/Bn#LN%L/}n5<kr^CX81A*g>4d&0Mx8y;e:>|fpe(yQ~P"
    },
    "Q": {
      "target": "Q",
      "data": 6213738732002,
      "hash": "phu(OXCx!`H]:wy`TisN%D`Q5#uCPE0pi0QPDsefn$V/+%??TQ/;v}8@J=W9lk]-K>tVb%Qrhe)-fS,{L}284o$=.6*qUa{lne%V"
    },
    "R": {
      "target": "R",
      "data": 2206153947828,
      "hash": "?^l2ig<pNqKS%`nYcHFSv<EZRK`+/VZk&])1Y08,gih?mE<q(h:7U5zkAn0`zVxr6*b1fSsx22)+Dec`m*6n;tUE<UqgVJx7S*Vw"
    },
    "S": {
      "target": "S",
      "data": 2326969179749,
      "hash": "z,wK}($AQRsuOp7+40^x*EuB0*m/*_R7xP(])GH~*jy(>P;;.BS(/18b<`{8L1![*1@wa4)RN)i66$(#Mwv`A?a.Ua`!Vmp2-Ikz"
    },
    "T": {
      "target": "T",
      "data": 3534054962243,
      "hash": "2$9>(UxLe?])1vI;MVmX!yn{aUrWixt_Ifa$x+lRrq}#/0GmH[~?5DO.]1Tp:Gq`b*S*_b6GV#5{r55rnM:ZbF&OuIDOoH`#+:@!"
    },
    "U": {
      "target": "U",
      "data": 5849301062572,
      "hash": "fpv|]HYhMi([K9>:0[^:_O!}5[IXX~Lt4$Z4%/g?&L{-Jv2g&i%J-cS?qYHPXB7bi<v+|NJH^u``25*zwvSWkuXdH0;EtP`!:Ka:"
    },
    "V": {
      "target": "V",
      "data": 7520047612273,
      "hash": "z6g}&y^GqS}:G01Fq3Y[w:$nscYLx:JEy#OS&zoTM?hqJ=.~RtA9aXFA20J}DDJhun{.JrrAHut&}vP{1)QJcPbWyquF#mZo-03O"
    },
    "W": {
      "target": "W",
      "data": 2980073955027,
      "hash": "k2>$T#3Hl4/w*87_Zfa:W9Olx2:YGlUvL~ItDDV#u.Qgm{f3KC*1?M>Vg2$#k]M8:Yz5h7E(6>D/=nJs@*_U.0_e^-ZK(i:=%c`("
    },
    "X": {
      "target": "X",
      "data": 2677666367412,
      "hash": "~(:TTJJ{gca!Ners%]vtC@gfs(^8p:ep(3*.^}h#j:}&JM&Ss=bmx]PLmOZ.tElH#n%Y*E+xj5irz-$]us)9HjkQ?xGpx`bRj|te"
    },
    "Y": {
      "target": "Y",
      "data": 9305436856676,
      "hash": "P*G[OpE^5`:3^M4]Hs#|n:-94S|68xXKihLZOq#~Vk]i_I{&kU>~$Oo>]DM0RT0Y`D4L?b4/C-jWHq|^n9V89km92kz5Wh%ds|Kr"
    },
    "Z": {
      "target": "Z",
      "data": 9252040571615,
      "hash": "]o>]G~3?Lhl1n5WYdM-BUQR]:*{{_&[*$0z>s|e_M>r`XDT:p*?kO`=;P.Vb:zOEN{w[i?v>fSe-th]C*.MPX=lAo~@kJK`KS!1*"
    }
  },
  "alphabets_sml": {
    "a": {
      "target": "a",
      "data": 3702935819937,
      "hash": ":n<jsUg-#c_0h5szjZ0XVT9,p3U}1X3ox`ZLJpQz(Pdq%Hi9V(P$Sw-FmTPNSEvOg+cPr*94:9s)Z)cHd3?Wy7Wjf[s[rxavf@C*"
    },
    "b": {
      "target": "b",
      "data": 7662598694945,
      "hash": "$*qt>:pj>!^u~O_#@2(Gt5Wu`1A.qa*0z&Cka`+HY>brH<`i3MS|rEh8O-wP5q/bC8*)#0}xZ?&?+Gx*)_Ivv*+.k~kMyTvZzJqc"
    },
    "c": {
      "target": "c",
      "data": 6908749972001,
      "hash": "@;6$U&W>#4qho<3VB@z4Dn;T=>x*b:i*@`t/`nH}76gH5vAE9V|MuwSvI`/*1?NTOo#Wk#nJDEv*d1SB1kbj0rxqB3#iPLYgI`n-"
    },
    "d": {
      "target": "d",
      "data": 6730921023753,
      "hash": "rPenyc~];F]B-**Y0+i%H4|)=ctv~8f+$9J%vPvnV=PU#f*kM1&]f^L1M`M*TzgN*,O&f((@Be_xm6!1-@b]0pfk!h4WbAW#f]nq"
    },
    "e": {
      "target": "e",
      "data": 6774327121551,
      "hash": "|qRZ9zCH+hle:nwT>~coWjo)AVib,?%]D_@c%](cT..7R&+as&yMy|t)^!vwyvB4LZ=+;79l6XFR5gCW+5noh^s(O__(a=,&IiYh"
    },
    "f": {
      "target": "f",
      "data": 4810920882166,
      "hash": "g)N$&4x$S:0:,cg?55%FuJnoy=ai*W9x7D<i!QL!!GT}~pnO3754kgkIKuo:@$D}isBQ`z:6R{G7:7t]duL~rq#44[w)52:o7emt"
    },
    "g": {
      "target": "g",
      "data": 2797600174551,
      "hash": "tXW;(Vcojo:jn~]F<?}<2v&x:tNTL$zb$!Qw.I:%~4b^(5:81P$B[O,mi*x/c{*JpK/NJA9!`2=cYT[5?x-7XkqQK2nl8,XuW0Ho"
    },
    "h": {
      "target": "h",
      "data": 6882525314745,
      "hash": "}GbAuqDH3-IdV4M(oL&Cz@n:Ba|`aJp1z2a|)QeJ8pl?75^GXoW1DNs@v7I*RERt[;QE$X:vwAUkRAB0hd:]&mk/A_Df)xMPfB_|"
    },
    "i": {
      "target": "i",
      "data": 6973219659512,
      "hash": "ZC1;6T:#e<WK]CDqd<7YC:-Ft487fS{[?.#iQZgm^QR>^*2GaNqO=p:LtsNVQ[Cd2qgCn*@MYdPr:VyO$bS4h-XQkbh$9Jo,]n]k"
    },
    "j": {
      "target": "j",
      "data": 7367339453023,
      "hash": "Nd9/CP]>xC?i2}bRF_xRpPKaoc`]73twkFN&lb*!-bX_VLm|HCoN7u1D;_*mPc8Lv]=1&ag.`#2*C:}xy<n[A]S;D-FRY`|*)R~["
    },
    "k": {
      "target": "k",
      "data": 8076351334549,
      "hash": "$(Kij=~DRnyQ`Ow*WZ,r5R@|C*hMXKdmTgMbU}E4`UV@tgLL:|r0Q*+Jijke?oSvRg!k2^H=68=ODI!kb*|toBn:I`z6.tsr{#C4"
    },
    "l": {
      "target": "l",
      "data": 8912975019087,
      "hash": "6sA;#Ps&sF~:pN~(*gcn]?n,c`A0b$K+5b,#-+fw`%iCfZTko[hKKCKeh,1}Qz!s/s*<lv*L8.6`8pWwc`1`b`c.W/yaN5`_B:kh"
    },
    "m": {
      "target": "m",
      "data": 9099227729521,
      "hash": "]_3,:QC9Wy:}ml*y}]&XPNT84>cs|c{7vxd%R`E_DfxGs{TDJV5%:XchQnmIk>X+duXqUP`DKk]%NW}I+d^M4+1<X90#Y;#ES9Ov"
    },
    "n": {
      "target": "n",
      "data": 5874356063872,
      "hash": "A|TWlN*am*M>E/_NrsGzslsrC9_BiM_;-kl!>]M<i?V@0~nG:<+**s]+#u5gqL}DA1bkMWE[leH-AF-,r*#/m*OqPnvfl%3`3`*!"
    },
    "o": {
      "target": "o",
      "data": 9837370338895,
      "hash": "51~uy(!xS_~?OsHs%;%TI:`}Y5Ft9e*o)^Ba0MDZZHmoFkW{rFR$.`n-?f$Nxd%5+y33y[F]G5MeG*n>|:9|*Gel-Izdma9q?Rt["
    },
    "p": {
      "target": "p",
      "data": 4847534863667,
      "hash": "(`!8p/D&/d*^&#=g(!?xB=,81JOel!(G/t5fy_`DX`KWiDUDd9h$vPRPZE@FZjbF#kc.S:*L5/W?W9c*hvJz_]Q*!OmTNuSci[zV"
    },
    "q": {
      "target": "q",
      "data": 3406337969549,
      "hash": "n;]<*slB2~7.#l_xuaMy#AMe^h-$6U{gA9QLfEzldOS|A;m/TWw5r6;T5!Y?kMV;Fm_D:&ueEbe|rCFYy@+f){%hICI-iN0ZI$<:"
    },
    "r": {
      "target": "r",
      "data": 7975869231857,
      "hash": ">J_SB.nn?5-o{&D:kAqI2[>DVJa=L/9_s`d`;t*zsIiN^gsRkt<l|:G~rI-s1a{c!tZx{vAGtuq3(4).[`c##@,`U9,0nSXslO8{"
    },
    "s": {
      "target": "s",
      "data": 5821457977600,
      "hash": "[*jNdVYO{$mUb?XF.1V3`kw)>nJ:r/$/IMY5bqry3{Ur*:sz.P{Z,DC~/Kz`~:`rZ7RhPCF+GFh+-<j>8}u927ouh*:mgGr)^vB|"
    },
    "t": {
      "target": "t",
      "data": 1397692512356,
      "hash": "sYBSu*.cb7!|#pMa4_Ea:d8T)D5$`Uklx>,Ulu)wXm)t6:+vp8yqtl?_y9/)^:;Ce0Q5`5Fkan#kZ+[huEUb|Wp{{9*hitYDvG>1"
    },
    "u": {
      "target": "u",
      "data": 5768339744057,
      "hash": "og[2s`^9m$8DC%>@m6CB}]FU`WnPDP~[v1dp-*bw4Ky1j#~hTaUkI|s-}|k=5-MK3Kr3f#K|4jz}yD1=w7?maK*P*.B`qn*J$`$w"
    },
    "v": {
      "target": "v",
      "data": 8261011769156,
      "hash": "Q;bgM+;?4VB%:7Hcwkiou*aDk~zL5t[hV:8=K9/F,790y(+3~]sY-X^4F<b)u#7[HDEO6S$@YOfN7De,8n`0e|DRk7O?`LJqm_vX"
    },
    "w": {
      "target": "w",
      "data": 2108529603653,
      "hash": "]|SQS}oj8Z2A!T-@lh$0}_;.t)pQu6yGt6n_i^oDQ}8m`q_yfis7k[3uL{eq(m[D*N!+o$xjK@g[2eSpG~K}sTsLs(Hb:MzkgYAf"
    },
    "x": {
      "target": "x",
      "data": 9993305052920,
      "hash": "7V%Kddf=T>tpLY{<9}6t:W.mTBJ{9ey3W.@nB{Q$QiGm&I{.y^+a:*wV3P[ja/L+Aiz~TXYjVbc$IE-ZW>^2_!gpmJ|ALc@uE>TR"
    },
    "y": {
      "target": "y",
      "data": 3250183925778,
      "hash": "*e:y3IdJ)n3bM@P}K+=lM]/S5GR^FhKIg/v<X_y>Vxu!y(c/Twuzh()R%@D)LRkq#8Z|NpqJVS~D[*Y[E4toC[P4/.-kR99:9a}-"
    },
    "z": {
      "target": "z",
      "data": 6649993998118,
      "hash": "RK4d>D$=A0Rgiz@w%*49cE]:7XN[LD9UaB|sn`*`;}P>GvOCY:4Vl*X6bhMgy@-n#HOl*lGN@Qf9<=zTq:81b~e(/y[7`?+!``~`"
    }
  },
  "numerics": {
    "0": {
      "target": 0,
      "data": 3213926770143,
      "hash": "%O8UJAU0CLdeLv+c]n20lT>[p.{:*<M,%N:nTI*!^SA:Xx.H2#L<l0M):?tgk>My}6qd:`T8RaW@VE{WU_~i:o:+lvIuG}!mDPzn"
    },
    "1": {
      "target": 1,
      "data": 2663329094322,
      "hash": "Jg1*c`9J5sXgXP8=ibEW*p#54yy2loZ[R$i}4B0wOsf_^`cW0cF`vmKCf7r=BOV)TdenZuaJg:bm;6*eyG-(D.n26KI`c{{MKBf6"
    },
    "2": {
      "target": 2,
      "data": 6915111617321,
      "hash": "qqKx0_Lm6jq34y;q!-<83Y2hJIAl&~f]JjL~c,[|Z*;{!i=KO.8fP|J9uO)a`y2R~xBt&<WjLc(*Z(UeRso-gokI-Qvj)sU2y~>^"
    },
    "3": {
      "target": 3,
      "data": 2536638136695,
      "hash": "1*JV/}La,6?PWa!fNG&-b:`j<m`mKU-]LNQ#d0uT`w*C6[t.(,=>@ks+E-2tc%]!Z4{R`0R:-Tw&|^4Z<?y]34c7C1oL?v=EeDbc"
    },
    "4": {
      "target": 4,
      "data": 7465811884725,
      "hash": "=Wg`*zkkGEu1~D0J!rh^YEaepM%pYn*)R/WFP]Ij^KDT$rDn*x9oT-,LAxZT.e#|;}k$]s-v0xVjbll*ABr+:~_bS{5N^5#uRI,f"
    },
    "5": {
      "target": 5,
      "data": 1942723085643,
      "hash": "@+cIqA?`&57M{`mvKcafd#M:|4EB#jt-W>l.G*|bF7>~ty:qL!v*a7[6aBK4ge)(Mz8=f0RXb:WBS|AcHSv,ZIE-<#X~b~%^9R#["
    },
    "6": {
      "target": 6,
      "data": 5956882070165,
      "hash": "hkhcAk8!)_,37mZ@=FX2;PsEI`Buk}*.JjOo71[W_cn^`f=pBd?3.`,k9ijUkhl,tBO??;yA8}(E[6$F!ZsNUuU_z|*C.2d]d;Jd"
    },
    "7": {
      "target": 7,
      "data": 5964151172116,
      "hash": "Jb.1.s@Uc^qZH}Tug/c)9nixs`F?s9${W8}*MCZF|>msTPNq3fFtb!&s%~Z:8Pa*pN63W29n^}&*IP6YyIw{b]3tUV`9%H@ZRDB&"
    },
    "8": {
      "target": 8,
      "data": 3365404776443,
      "hash": "EoDS>Q$OsLQIJ.&CsT#EfxQFDXHvE1xCjbFXZGhsLIlK-1cPvtd.3*QSh@`^y@/oWUy{:6zNRR3LhfI8q,UN`HSEQR/M8kwUtXVI"
    },
    "9": {
      "target": 9,
      "data": 3173445249669,
      "hash": "9bi{Ulj6.H8C3~GE6Y,?-v8`&6Z-cNKq2J=REA;VJV`Z-z#w`k[:b`ptx3q2S*bePF]p`]caH483{`:{%}7l.&<R<<e}w$H:]oWr"
    }
  },
  "spec_chrs": {
    "!": {
      "target": "!",
      "data": 4478368932580,
      "hash": "Qqj!WRCWFm|ks[!=VSOUXsS|dRf_+%75CLCIFQ+*SN~uVR~qna.BCL:;:5&C7?FvmrfmMdzEdIoR)`,eJd|yaBANV--`kZ/a:^)#"
    },
    "\\": {
      "target": "\\",
      "data": 2347784356237,
      "hash": "lL^G0dX%wOy(GF}r*3eP8F6j?:jUD>udSaZNJ*-1}U=,^Wr_]AXd7Yjl*=T)cK]llf5KXLSr=G6C=%cKVVBdzY&/h{!aN8<MHo1y"
    },
    "@": {
      "target": "@",
      "data": 7042037868869,
      "hash": "?r_xm71<eIs#aU-B|/4I{=0F3^uC(vL<y..HgUp=EV<@^iK{eom~kOSbVbK.zZ:CL}a`xb.~$MxiPmM%q81vGr;fOH(NNuA[27.Q"
    },
    "#": {
      "target": "#",
      "data": 2351067389607,
      "hash": "v/{)lH~.q{V-pAd}D4`C,cHO=QJv:lp$f6eT92H}SNg@|f/y>X{V_{Ji@4.?2q>gknOM9Uxd?WfE)jtKi)FS!&R:(Ialt*GHYh<]"
    },
    "$": {
      "target": "$",
      "data": 4107565039604,
      "hash": "VY>,CH<p{{Y5<2*^dsXEJ;**,hr]P@u{[+^~>DYElPFEP!;?^,r:?}>~*k/rc&b+X`J<e5-`y&lzuY(bN`D@kR@XTj6tb=KD**|z"
    },
    "%": {
      "target": "%",
      "data": 4979021136843,
      "hash": "W)sV$C:8r:fz5z`get.hWX6<aUje:dT9?*@A?g[r9Kc9;yj$i`=:EL.iG[9hrtOE<YAp$QilJG@/aU]T<$H<-TBjQbHThr75SQ5="
    },
    "^": {
      "target": "^",
      "data": 3772578369507,
      "hash": "YX@bR8ZAuV9}nj*<*p/(x)HD9R-Ioo@=EA}>Gmn}Sh.=tRI::D*O1;JeI}p_O#,>|]vB^`=-e:T(fk`t*,;7zw?38~GW{Qqsxi#P"
    },
    "&": {
      "target": "&",
      "data": 8621013791886,
      "hash": "h*3!`Cp7ldPJznBDs9Whw5FyLl$r?9UXg~=jX-{ga$]fKy)J^O]T?5TgRnLdUiIKVSo:rA7dbdaH.MEa:=^tv>$1$%FyC)WKL^?2"
    },
    "*": {
      "target": "*",
      "data": 4162509853558,
      "hash": "{~L<t]R:DWms>WE5VBmab),G`%-;s/]t;nm`d:*IR$Y0*j@2P/mWb]!6<~1g;y$g|n,_1{z?Dy{x}`I[dj$dgY0qJ6^$YG{ZCjb`"
    },
    "(": {
      "target": "(",
      "data": 1794109993917,
      "hash": "8HSNIgB#>!n>q4Xwrcj|+l0n6%0kvC(`h4vymE*NOLq|uh=`Ao>mu0XaXpJyprt-XURaz*ECv^r0vCCs#TTB_a/7xH~L3?/}k%G*"
    },
    ")": {
      "target": ")",
      "data": 3984246961329,
      "hash": "5$(9&jjDygOZV[BdY`pwpH<+S1}(&2;XJBgWr9POgyuO]%NYI0Ba9b<wk>a1zyJWRM%xZ$^P0*0.C(KA#@GB~`;_LMg*X$aNu4n7"
    },
    "-": {
      "target": "-",
      "data": 5595575051282,
      "hash": "}G,2IDNKjUyg2)z4KMuR(ZJR~T;DHE1@*udO}aHO+3U+OWv11%80N+.5#@oY!mH#@SA!rv=Xk*q3RwQn:6`YI[8``X{(`|t{SfMB"
    },
    "_": {
      "target": "_",
      "data": 9905438241868,
      "hash": "f2F;hiHpGf[`>6OX?bKqZ@]U9a4<VGSy>JI>YebLv3@Z&oQv$!1A23G0RTC72N-(8~qFEi:lKov?h`D53#0*CwHtUK1%[Jnx@XE,"
    },
    "+": {
      "target": "+",
      "data": 1447672315609,
      "hash": "&3lE-zNRJii?Xw4${uI>)FkwTFt=H5|?l+Pws)/*Li9mv{8:/oI;)@QM-iXk}3zfigED?7DV;=zH`:)Z(s<RK_V;gVyyS(JVkTK["
    },
    "=": {
      "target": "=",
      "data": 4760119523135,
      "hash": "u@XG;iWq)m+1~$mXb8s::5*^<:=CNg$6<%AaVx>5s?jiS<0z]R4exvG!TG:ogT=p}|@tU3i7kV87:eaD-e?T`,8z.uI;TD`!U73:"
    },
    "{": {
      "target": "{",
      "data": 2896057044519,
      "hash": "D,nEtV:g9m7|R*sp#1lWvpN(Mi=y::q]n`>E~Z*6Yj55gIE;#%,j(m.ZyIHI/Ktv*qyNsv|(h]LBc1knB&{lb@&r.ZoY+RNpgpu%"
    },
    "}": {
      "target": "}",
      "data": 7558573885421,
      "hash": "R}Q21a7VOt.kY8s:f(1*Mr(qi+/ON&g:hGvqv]h+/`g%c9!<a!Db5ZvctEdhR`mle^DoNGMA`1=/e;IckT:4]c$4w$3gIpu1U<bf"
    },
    "[": {
      "target": "[",
      "data": 1254015162910,
      "hash": "]S&WVO?ePE!;Bx<P:qsOd4z.P_}cZQpE5K9Xo7Bo/S._+t{a/qtc9eK,JltaRu+r{J:4k;jy0S<UaIh=qFp#$L8;c79bo`OUd:Mx"
    },
    "]": {
      "target": "]",
      "data": 4172855318049,
      "hash": "iBC(8?%l5^(JR4BJ:4wb9D#KxB~xN)&2{TmNSm}E>xx5DG-1q$EzD:?0?aEy(<eXW=8Qq+|]o,b7Rja4pjqP#3QW/d4k`i>ikZ*["
    },
    ":": {
      "target": ":",
      "data": 1350009115172,
      "hash": "onFs)U0=!_?Z(j11}~AJ=O^~&h>h*Oy`f%^n@[m2k:CBlY5&6LqnHJx7&eQHS@+^spOkt/73/A-6KeOo[b*w**uio^$WqJO,8RCy"
    },
    ";": {
      "target": ";",
      "data": 4145181973131,
      "hash": "*EmLWA:lgq67j?:-&$7*|kL;a.&w5|?&/hXN3Ti/RwQ`$TQD[+$|*vj4)Z%pue%8FIzXW3A6<rut#w3!C~[eLmdl<LL|c!ExFC|*"
    },
    "'": {
      "target": "'",
      "data": 5812076522655,
      "hash": "sI^3L~{ozlQ-E*xr>xAbAgc[D7ek$HTj*-)a3(#b(4WZ49+aP84GEDf2h+(-VgHE8j?5;kW~+9Y.(j3t2rhr?+Li8&rSw$hs.ZwW"
    },
    "\"": {
      "target": "\"",
      "data": 2394812905012,
      "hash": "Xq+R$TcYDZf&Mu[M8a$]?Chsg3CYJzrjD8/kLijEL,DM~,4Q:U+<IKD6J4Da;z0p=:Q`|8z|bwa#4[C,6gE$NLn]0nj$H8iFvaPd"
    },
    "<": {
      "target": "<",
      "data": 8796844427373,
      "hash": "[!F0;W@?U8.j%Xe<7RC)_{-]8<!Wvs).c.db2kjS)sUQR}D09+0C(>p<,^L<{2rK&~trK0x)p(/NO<-.N0V:+NYg7t#8`|t1SHD|"
    },
    ">": {
      "target": ">",
      "data": 5438971515462,
      "hash": "L9@xYj#wXDFR,Kp72Po6-AK=pHg{):M#7<^ytb!bPEOB!3z3K+X*Wrnd,20jV<T_]Vb)B{>:C3*I,Q)IT]:*l!e|c1%q%~;hgj#6"
    },
    ",": {
      "target": ",",
      "data": 8612479978900,
      "hash": "Db9#Q87_$W]`F%--WWd*Ff^K)*`W`/D;Vvr5j(p;^*:9h:;cxaW:NryMgC>?lEg:^$W5c907Z~]}V@if,1wEJBWn-0?R{tbZn:P>"
    },
    ".": {
      "target": ".",
      "data": 2867366707242,
      "hash": "B1cL`Wu$lV/qm<VMIg`]xtY{NM_mB7kgBQV_FP~uREd:j<=Z`j@+vAha)S_2n-]Da1.2bo1xFSx~;WMI~j^]Rl$!X])f3NIFa{q!"
    },
    "?": {
      "target": "?",
      "data": 3469597120225,
      "hash": "n2K{4J+{Uf[2I(1m?rQb9(}=?Le9RXXZb$@Scqh/RU:+!myxPc($4=:qB1*,;P>>Q|<`?kv1by*yn=`e).D.>M<STTfTqj_&rai%"
    },
    "/": {
      "target": "/",
      "data": 5654598609173,
      "hash": "OpFSs}v1XYlPJG5p/*G<Su:d:aMi,NG+`9N%NQr8TLYHt&|56/$BIA%F#`3/R4*OPlRdj?4!*ezjWYd,5GN7b&vR|;I4I$SF}N2*"
    }
  }
}